{"firstName":"Sadie","lastName":"West","email":"tremayne.gulgowski@gmail.com","phone":"(298) 226-8553 x034","bio":"Molestiae consequatur qui facilis voluptas nihil sed et voluptatem. Voluptatum ea qui aut quis doloremque tempore est. Quia iste eum perferendis dolores quidem.","price":64638,"is_verified":false,"company":"Watsica, Bauch and Kerluke","time":1525004127,"about":"Enim veritatis eum omnis eligendi ipsum atque nihil aut ratione necessitatibus qui quod vero dolores in et tenetur nulla iure vero voluptatibus odit itaque quis minima et sequi et ex a quasi incidunt corrupti blanditiis dolorum quas provident cumque vero quis quia beatae iure dolore quas repellendus rem eligendi accusantium dicta voluptatem quisquam cumque ea ratione quia distinctio nisi eos quae delectus quia maiores tempore enim dolorem ipsum ratione quos ut praesentium corrupti aperiam adipisci doloremque rem magnam qui et ratione aliquid et voluptatibus sequi harum quo eius aut sit consequuntur blanditiis quam aut et tempore itaque voluptatem mollitia consequatur eos voluptas iure illo porro dolorum voluptates ullam qui cumque magnam accusamus et fugit quasi veritatis expedita sed tempore adipisci accusantium non soluta minima magni fugiat aut quia quos ex dolor ratione dolore voluptatem voluptas consequatur tenetur dolor quia est ut aliquam rerum autem omnis facere est dolorem nobis reiciendis corporis velit consequatur non pariatur nesciunt corporis autem earum rerum excepturi delectus dolorem et itaque modi consequatur et et sit possimus non exercitationem quia nesciunt ipsum qui totam omnis nemo id nisi expedita cupiditate amet quisquam unde corrupti quisquam aliquam voluptas dolorem recusandae qui laudantium delectus est nesciunt rem nemo iste dicta cupiditate vel amet necessitatibus est cupiditate commodi nesciunt rerum qui in aut voluptas vel vel ea ab ad id non temporibus omnis sapiente incidunt tenetur animi voluptatem ut labore fuga at iste ea ab ipsa labore est minus quia est sequi quo rem qui alias eaque libero natus omnis consectetur cum veniam alias maiores ut sint delectus delectus ut nulla explicabo possimus id ut quas est maxime est harum consequatur ut id eum autem facilis optio consequatur qui doloremque at quos qui et ut qui aperiam quae aliquam pariatur consectetur reprehenderit adipisci pariatur autem maxime culpa labore earum quasi saepe animi molestias suscipit asperiores blanditiis corporis nam animi voluptatibus eos nulla consequuntur velit ipsa dolore earum aut nobis omnis magni non et delectus deserunt tempore qui delectus et sint autem aut voluptatum velit quibusdam esse error voluptas praesentium iure quibusdam velit nesciunt rerum rem est quisquam veniam ad rerum non voluptates ut aut molestiae non rem quidem est quia est facilis minus laudantium nesciunt rerum vitae molestiae qui enim aut nulla accusamus quae ea dolorem omnis animi eum corporis eos est magni doloribus a debitis repudiandae voluptatem velit et quo quis tempore temporibus tenetur saepe atque eius quod possimus excepturi praesentium impedit est sunt ut et ullam doloremque nihil commodi ea in eum quia alias ad ut dolor ea ex aspernatur quod enim fuga rem deleniti consequatur qui excepturi quas illo ullam est doloribus provident minus sed quis voluptate.","address":{"streetAddress":"440 Jana Extensions","city":"6161 Federico Square\nPredovicchester, FL 04288","postcode":"94278","state":"Missouri"},"article":{"id":9,"title":"Perspiciatis ut voluptatibus eaque.","text":"Sed excepturi ad optio cumque dignissimos laborum molestiae omnis autem omnis et ad quae suscipit quas exercitationem deleniti architecto qui impedit ut inventore quae tenetur aperiam numquam eius blanditiis laborum dolor quidem quia ut animi quam nulla quo iure est delectus ut iure earum voluptate eos ut voluptas molestias ut tenetur consequatur est veniam nobis necessitatibus maiores recusandae cumque ipsam laborum eaque sequi earum laboriosam cumque et magnam dolorem qui minima fugit quae veritatis minus sunt modi autem facilis non aut earum molestiae molestias aut velit est qui ex laboriosam dolor officia nemo voluptatem vitae rem cupiditate aliquid voluptate molestias quaerat reiciendis quia perspiciatis quaerat in illo autem eveniet quia nostrum asperiores nam quidem sint omnis quia aut et maxime quia unde sed impedit id consequuntur et deleniti asperiores dolorem placeat eos veritatis vitae eum et ea eos consectetur vero debitis laborum doloribus suscipit dolor eum eligendi quo dolor temporibus repellat est inventore earum unde ut natus quae et facere ipsam aut consectetur qui qui maxime ipsa quo et omnis aspernatur et deleniti laudantium nobis et est dignissimos error voluptas alias facere et qui tenetur voluptas facere sequi nostrum porro facere quis id et dolorum quis odit et atque dolores animi ab modi earum ab sit quisquam esse rerum magnam reprehenderit voluptatum minima blanditiis aut porro tempore aut eum voluptatem iste dolore porro voluptas sed aut consequatur voluptatem aperiam temporibus praesentium commodi voluptates voluptatem similique velit dolore earum inventore nulla aliquam deleniti quia harum tempore quaerat dicta tenetur animi dolorem odio non ipsa aut dolorem temporibus quis cumque voluptatem aut officiis ipsum delectus et et provident vel ut at iusto deleniti enim perferendis et voluptatem cupiditate inventore cupiditate quaerat quia atque iusto deleniti tempora voluptatibus rerum labore eum aperiam omnis doloribus fugiat accusantium animi voluptas officia ipsum quisquam illo fuga cumque at doloremque blanditiis et dolorum enim accusamus neque omnis aperiam corrupti eos et eaque iste sit laboriosam magni voluptate suscipit magni sit iure ullam et ut vitae fugit a ad dicta aut ipsum beatae et magnam culpa cupiditate libero vitae pariatur labore ipsum quis voluptatem quasi est dolorem aut qui sint qui blanditiis labore aut aut autem repellendus ullam quos est exercitationem quia impedit dolor laboriosam ipsam quis minus quia qui esse nihil occaecati voluptatem facilis alias aperiam eaque est blanditiis aut maiores velit odit eaque exercitationem rerum iusto velit itaque nostrum soluta dolorem laborum omnis dolor deserunt vero et minima nesciunt rerum omnis blanditiis vel impedit dolores culpa architecto repudiandae debitis ea occaecati autem est et doloremque ratione voluptatem ipsam aut corporis nulla culpa blanditiis magni et repellendus non facilis illum nisi reiciendis perspiciatis doloribus atque voluptas enim et et molestiae dolores adipisci nostrum necessitatibus enim nam voluptatem eos quia dolores repellat totam optio ut nesciunt eos tenetur aut et quibusdam totam quia aut est et qui assumenda repellendus commodi a aut magni odit est eos nobis magni est cum totam qui molestiae sequi rerum consequatur ipsa provident voluptate ducimus ut nemo incidunt quis ea perspiciatis illum nam qui cum dolor voluptatem natus architecto ducimus eos molestiae ut sed sed blanditiis quia accusamus eos voluptatem eaque est id voluptas explicabo impedit officia nesciunt corrupti et repudiandae quo asperiores accusantium autem et aliquid expedita nam sit quae dignissimos in alias delectus sint eos quia velit qui et odit vel et dolorum aut veniam quisquam accusamus saepe eius corrupti et facilis qui totam enim qui in ipsum delectus quia quia dolor neque et ut aut qui corporis delectus quos fugit nemo ut et est a itaque quo id adipisci corporis fugiat blanditiis non culpa nisi voluptas praesentium qui corporis perferendis ullam et impedit facere eum maxime vero sint iusto neque facere iusto praesentium ipsa labore repellat modi pariatur est et ipsa ut quis veritatis consequatur quia cupiditate ipsum perspiciatis natus eaque enim unde ut eos eaque ad dolor est eveniet sit aut quasi unde architecto est ad aut tenetur ullam maxime ut at expedita qui et autem beatae magni iusto quaerat nobis sit velit architecto sunt accusamus quia quo quasi neque et est praesentium ea qui temporibus ut deserunt recusandae illum vel facilis error ut quisquam tempore quam ullam et reprehenderit dolores magni ipsam sit molestiae vel amet ex quidem magnam ex quis earum nihil quis labore minus commodi iure est ut sed veniam ipsam quae rem dignissimos sit qui illum architecto sint similique quis porro sit sint ratione sed quidem repellat veritatis veniam consectetur dolorem facere incidunt et inventore quis voluptatem qui qui quas vitae incidunt dolorem amet cumque quas optio porro error dolores ut et velit et ducimus ducimus sunt quae quas nihil aut placeat et nesciunt exercitationem dignissimos suscipit eligendi aut voluptatem maiores voluptatem corrupti harum rerum suscipit et nulla sed eum esse voluptatem nihil eius hic aut nostrum dicta officia in doloremque ab nemo ea quis in magni nulla et cum et impedit et animi reprehenderit aut aut reiciendis corrupti sed dicta quisquam beatae sint vel in voluptatem at tenetur quaerat blanditiis ullam magni qui et voluptas eum est modi totam dicta dolorem error aut ut optio est nemo unde ullam alias ut quis praesentium sequi ut hic sed nam quos repellat ullam sed sed et ipsum aspernatur vel voluptatem esse recusandae non aut illo laudantium ratione quis temporibus illo optio et autem excepturi quod iste nostrum qui aspernatur quia voluptatibus fuga ut sunt ut nihil enim soluta nostrum recusandae sint quibusdam ex quibusdam magnam at beatae totam voluptatum inventore dolorem fuga quam et earum ipsam dolores omnis et et voluptatem incidunt odit in unde nam omnis et quo est velit sed vel sed molestias id debitis rerum aut dolorem rerum qui sunt asperiores blanditiis voluptas dolorem rerum quia aut rerum est enim eaque incidunt et porro corrupti inventore aut velit qui laudantium doloribus provident eius quas quia et sapiente alias dolor libero libero veniam ex et dolorum quia error molestias sunt minus sapiente quo occaecati libero et nobis voluptatibus blanditiis aperiam maiores aut dolorem necessitatibus sint rerum sit quia voluptatem a doloremque eius ullam sint molestiae dolorem assumenda est aut iure vero sequi laborum aliquid sunt dolorem dicta molestiae doloremque quia nostrum in numquam quod magni illum quas fugit nostrum et et inventore magni id quibusdam quia accusantium commodi et necessitatibus alias commodi similique modi similique rerum id tenetur sint nobis nesciunt sunt molestias vero sed id eum illum provident quam dolor itaque alias deleniti non nostrum doloribus rerum quibusdam aliquid magni laudantium quasi vero in saepe enim nihil suscipit sit porro dolorem et omnis est ipsam iste libero officiis ut et et facere expedita voluptatem rerum cumque et minus mollitia temporibus eum ut nostrum dolorem itaque ratione ut et et nihil in sit magni voluptatem ut voluptatem cum repellendus cupiditate sunt qui voluptas distinctio eum expedita qui blanditiis in facilis et est est repudiandae minima occaecati voluptatem quia repudiandae sint necessitatibus voluptas omnis libero sunt consequatur consectetur aut labore commodi sequi consectetur ut omnis placeat quae exercitationem aut necessitatibus natus aliquid molestiae architecto temporibus deserunt est sequi tempora aliquid et suscipit nesciunt sed velit consequuntur consequuntur ab occaecati architecto beatae ipsam nihil minima sit doloremque ut et id iusto iste veritatis earum aut consequuntur omnis sed aperiam fugit pariatur earum quia quos autem mollitia modi magni enim veniam similique et qui reprehenderit eligendi earum consequatur dolor dolores earum consequatur qui omnis non animi distinctio cupiditate architecto facere aperiam debitis voluptate natus corrupti aut error beatae cumque possimus quam architecto fuga odit nostrum et velit et est voluptas quia aspernatur eveniet eos consequatur esse minus est pariatur dicta iste quis iure et quos totam asperiores perferendis rem reprehenderit corporis eligendi soluta ut sint aliquam ut consequatur magni voluptatum laudantium ut suscipit culpa tempora est et et voluptates ut autem et qui consequatur perferendis in sed earum."}}