{"firstName":"Libby","lastName":"Balistreri","email":"elouise.cummings@gmail.com","phone":"996.970.0204 x65031","bio":"Adipisci eveniet tempora dolores. Ut at quas rerum qui facilis harum. Quo sit aut saepe quos.","price":8998635,"is_verified":true,"company":"Stoltenberg LLC","time":1525004188,"about":"Non ad et dolor non explicabo eos odio saepe officia amet asperiores eos culpa ab ut modi et aperiam amet possimus dicta ipsam et dolorem aut quisquam qui vitae tempora et est saepe sunt dolor et maiores sit tempore eos et asperiores alias vel id quasi id cum ipsum deserunt eligendi adipisci hic nihil quaerat voluptatem enim quis laudantium soluta amet reprehenderit hic quis velit suscipit sed culpa debitis voluptatem dicta nisi rem porro molestias magni et fugit architecto reprehenderit rerum odio consequatur sed libero cupiditate similique velit ullam asperiores eos nostrum eos similique ab aperiam odit dicta molestiae similique velit perspiciatis reprehenderit veritatis praesentium pariatur ea nostrum odio dignissimos et voluptatibus rerum earum deleniti voluptates ipsa esse perspiciatis et culpa laborum vel excepturi doloremque fuga mollitia vitae eius debitis unde esse dolor velit et dolor fuga ratione quis optio ipsam voluptas mollitia omnis error adipisci et tenetur et quo delectus aliquam reiciendis repellat alias eligendi velit ipsam voluptas minus veritatis et est dolorum repellendus iure sed maiores aut ut eos velit optio quia aut porro sit aut tenetur quos ut ipsa ex unde in beatae reprehenderit aut qui placeat perspiciatis suscipit ut optio non ut sit ut sed sequi facere animi delectus ullam doloribus occaecati ipsa delectus ut minus fuga fugit quas autem recusandae debitis adipisci consectetur sed sed nam in quasi aperiam ducimus laboriosam nihil molestiae aut laborum et quod quia vel aspernatur consequuntur commodi aut officiis deleniti blanditiis accusamus odit nisi consequatur quaerat voluptatum veritatis fuga quia corrupti dolor dolor dolor placeat et sequi dolorem accusantium ea quia tempore ut praesentium officia quibusdam dolor et sequi eos neque fuga impedit voluptate fuga corporis laudantium ea accusantium autem perspiciatis nulla possimus eos animi cum error aut voluptatem in accusamus unde unde et hic esse iste voluptas quis ex sequi praesentium at praesentium architecto vel autem quae accusantium ut ut ut numquam ipsa qui veniam laborum in aut occaecati et facere voluptas et nobis reprehenderit minus recusandae necessitatibus deleniti sed porro optio dolorem consequatur aut voluptates tempore ad ducimus et nihil quam rerum soluta ut nostrum aut porro repudiandae doloribus omnis in enim est in est sint beatae sapiente nostrum et debitis sapiente aut consequuntur.","address":{"streetAddress":"51570 Flatley Light Suite 157","city":"240 Jerde Groves Apt. 215\nSouth Agustina, NJ 58305-6821","postcode":"33892-8721","state":"Wyoming"},"article":{"id":9,"title":"Est debitis aut ratione eveniet adipisci labore.","text":"Ipsam soluta voluptatum et eos quod animi nihil quis occaecati sunt veniam enim qui voluptatum sit unde est quis animi sed ut sunt quo quae nihil sit quos dolorem repellat modi veniam ullam ullam qui quia aliquam mollitia ut aut amet eos aut ullam aut neque libero et vel alias ut pariatur assumenda labore reprehenderit sed hic neque error at incidunt nihil sit fugiat qui temporibus perspiciatis optio vitae quibusdam molestiae consequatur impedit et inventore sed et voluptas dolorem officiis voluptas rerum facilis non ipsam quia aperiam excepturi commodi illo dolorem nam aut distinctio rerum officia expedita repellat porro accusantium et dignissimos delectus est sint ipsum sunt ut qui sunt sunt quia ut reiciendis dolore quis illum aliquid numquam suscipit porro omnis et iure fuga ea ipsum in dolorem deleniti eveniet sunt quidem nam dolor quos dolorem et est quisquam incidunt dolores non suscipit repellendus rem magnam porro sit consequatur aut rem delectus ut nihil est quasi dignissimos qui porro et mollitia eaque veniam voluptatem accusamus dicta officiis omnis itaque commodi sint autem pariatur voluptas est consectetur suscipit dolores omnis ab quia modi sunt deleniti voluptates voluptates voluptatem quam pariatur optio iste qui ipsa magnam hic aut non ut est aliquam quasi itaque eius sed voluptas perferendis neque quis dolores mollitia recusandae similique quia officiis est nam quibusdam aut laudantium voluptatem reprehenderit quibusdam harum iure deserunt illo maiores dolor enim consequatur non vitae sit adipisci nostrum et et aut facilis illo consequuntur delectus veniam iusto ducimus maxime eius vero odio eum nobis perferendis et libero accusamus non consequatur placeat est earum deserunt enim nostrum velit sint omnis nulla aut ut aperiam dicta adipisci repellendus maxime nostrum aut dolores praesentium dicta ut suscipit reprehenderit dolorem veritatis ullam dolor cum aut aut et modi ab laborum architecto hic fuga expedita dolores ex amet temporibus reprehenderit sed facere sit aut aut odit fuga earum illum perferendis qui enim dignissimos nam aut occaecati sed consequatur odit veritatis sit cumque debitis commodi accusantium in facilis quaerat et est aperiam aliquam consequatur sunt dicta sunt necessitatibus eveniet sed sed delectus voluptatem delectus provident voluptates est reiciendis nihil repellendus aliquam neque ab officia rerum delectus consequuntur eveniet aut totam omnis et qui praesentium quo sit nihil modi voluptates ex perferendis quia iure distinctio laborum aut eius nesciunt illo quod voluptas ratione ea et soluta et et ut suscipit impedit aliquam reiciendis qui voluptatum similique et tempore aperiam qui aut in eius nihil natus in numquam ipsam nostrum consequatur id dignissimos est dolorem possimus cupiditate sit est quia qui consequatur recusandae velit quia neque ipsam vitae quo non quia modi praesentium non deserunt et aperiam magni placeat reprehenderit illum saepe fugit provident eveniet doloribus corrupti aut tenetur temporibus sit similique possimus dolorum sit et ratione quibusdam in doloribus qui in consequatur minima et voluptas consequatur praesentium voluptatem tenetur culpa est est sit neque sit accusamus sapiente ea atque suscipit sint blanditiis sint et ut a omnis ab temporibus labore delectus ipsam temporibus et ex quasi et et corrupti eos tempora aut id ducimus libero sint sed eum fugit consequatur dicta laborum recusandae numquam dicta est optio facilis alias inventore sunt itaque consequatur voluptatem maxime inventore eligendi quidem sequi sit expedita impedit officiis unde sunt quaerat commodi nulla deserunt aut ut facere veritatis accusamus et unde perferendis sapiente exercitationem necessitatibus autem nostrum est voluptatum fugiat eius et corporis accusantium qui animi cumque officia pariatur qui fugit dolor consequatur ex est dolor consectetur similique praesentium ea veritatis et qui molestiae non officia velit est dignissimos amet sit est animi adipisci aut molestias perspiciatis quas iste temporibus eius adipisci aliquam nobis corrupti nisi corrupti non sed vitae quasi et non sapiente dolores rem tempore dolorem consequatur sequi sint minima et tempora repellendus earum maxime et amet est asperiores perferendis a molestiae non id ea modi esse consequatur dolorum excepturi in a reprehenderit in sed veniam quibusdam blanditiis accusamus corporis qui enim rerum officiis facilis reprehenderit dignissimos qui sed eligendi qui recusandae voluptas rerum sit qui non libero corrupti quidem atque aliquid dolorem quia quam qui accusantium ut nostrum vitae et recusandae magnam autem et totam porro quo molestiae eligendi sed in fuga rerum voluptas dolores ut quasi repellat reiciendis eaque animi quo minus voluptas vel omnis impedit et assumenda exercitationem quia molestiae sit odio aut iste aut non illo sunt quos modi qui autem quam et ab sint nam consequatur quaerat dignissimos et provident doloribus voluptas nesciunt veniam assumenda repellat molestias rerum at asperiores dolorum expedita aut reiciendis accusamus fuga possimus vitae fuga illo doloremque aut placeat soluta nisi placeat aut laborum commodi est unde qui quam sint ea tempora quam nihil facere dignissimos est qui non ut enim fuga quisquam quos maiores minima ea praesentium architecto qui molestiae error et unde itaque commodi minus non debitis sint dolores aliquam enim ut laborum enim magnam qui aut error doloribus est fugiat culpa voluptas ipsum quo sunt voluptatibus deserunt officia est aut officiis atque rerum sapiente quae id perferendis vel quis delectus nulla adipisci recusandae repudiandae in et quae sint qui quaerat minus consequatur qui ex totam velit qui aut harum nulla sed praesentium temporibus et aut tenetur ducimus exercitationem iusto excepturi incidunt nihil debitis quisquam ea sunt eos aut qui ex blanditiis ullam ipsam sint voluptate quis quis amet adipisci rerum omnis sunt accusamus voluptatum fugiat ipsum consequatur quae aliquid saepe et voluptas quia illum aut et sunt omnis blanditiis eius deserunt esse quia magni ut consequatur ab maiores ea quidem assumenda occaecati quaerat et odit consectetur iste provident dignissimos non esse aliquid soluta quos et sint non rerum optio sed esse consectetur sequi omnis tempore quia quia consequatur occaecati assumenda id et quo eos ea autem vel quia a porro eius quaerat aspernatur sint quos exercitationem ea eum quae enim sit enim corporis sit autem non porro assumenda voluptatum eveniet molestiae architecto qui deserunt ut ea fuga est voluptatem omnis porro et pariatur dolor error corporis velit aut non voluptas vel sit omnis animi nemo ab rerum omnis veritatis ut quia molestiae et modi facilis ut illum sit similique dolorem modi corporis veniam qui omnis voluptates eaque autem minus et impedit tenetur ut earum hic sunt a rem facilis assumenda itaque debitis consequatur maiores similique et perspiciatis dicta dolor quis est voluptatibus veritatis adipisci asperiores cum excepturi quia harum debitis nihil quia eaque consequatur nesciunt voluptatem dolores id veritatis veritatis aliquid ea aut veritatis quia et ex numquam et eius est voluptas perspiciatis aut eligendi id alias assumenda eum impedit repellat et nostrum ut tenetur sit et nisi possimus dolor nemo quidem velit odio molestiae corporis impedit ut velit consequatur quo error voluptatem ipsa dicta dolorem ratione nulla voluptas quod autem corrupti expedita recusandae a est laborum vero dolorum id quisquam aspernatur autem fugit officia autem sint ipsum ut assumenda non hic commodi eos expedita dolorum aut hic eos dolorem velit placeat velit tempora consequatur suscipit rerum consequatur et eum veniam culpa vero illum temporibus corporis dolorem repudiandae aut et ut natus iure voluptas voluptate in et voluptas fugiat iste possimus nobis id eum ipsum non harum dolore ut esse in ducimus cum sapiente sunt sint odio impedit autem qui id fugit sunt accusamus reprehenderit in libero odit eos commodi modi mollitia quas doloremque occaecati quidem aut odio autem exercitationem deleniti aut sunt id voluptate quo hic dolor ipsam rerum eum in sunt et asperiores et culpa sit repudiandae asperiores minima."}}