{"firstName":"Bradford","lastName":"Fisher","email":"cesar56@welch.com","phone":"+1 (737) 498-4703","bio":"Velit quia sed quam non fugit. Maxime nemo voluptatem saepe eum. Dolores assumenda distinctio dolor consectetur sapiente.","price":9,"is_verified":false,"company":"Smith Ltd","time":1525004357,"about":"Quia esse magni qui tempore enim voluptatem praesentium provident animi debitis veniam sed quo omnis ratione dolor molestiae architecto iste mollitia ut omnis rerum accusamus quis quo culpa iusto molestiae reiciendis eveniet culpa inventore non enim reiciendis similique et iusto eum modi facere alias dolorum quisquam sed ut iusto autem doloribus unde accusamus eum dolorum veritatis sunt tenetur totam incidunt eligendi est dolorum qui est voluptates est qui nihil et quis voluptatem tenetur molestiae rem sequi ut in temporibus repudiandae odit sed autem rerum numquam error provident et rerum tenetur unde cumque aperiam itaque impedit nihil inventore quia omnis eveniet assumenda laboriosam perspiciatis corrupti dolores id odit molestias delectus eos facilis laudantium voluptatem accusantium sunt ut excepturi in dolor voluptatem soluta assumenda et fugiat ut et molestiae ut corrupti qui itaque iusto pariatur maxime et et voluptatem facilis ducimus culpa vitae culpa incidunt qui voluptas doloremque voluptate ipsum adipisci et sunt quidem beatae voluptatum sit quaerat quia vitae dolor omnis quia a assumenda est architecto enim vel delectus rerum officia ut qui voluptatibus eveniet voluptatem reiciendis ullam rerum provident quam officiis dignissimos repellendus blanditiis quis veniam reiciendis alias aliquid velit distinctio ut et sed debitis eveniet aut sed et dicta et rem aliquam labore non voluptate fuga pariatur dolore et rerum ipsa dolorem voluptas ipsa ea qui et laboriosam vel molestiae sequi ipsam eum aperiam qui aut autem et accusantium vel sit quo aliquid molestiae enim saepe eum doloremque eaque non quae qui deleniti neque et porro commodi autem quam sint itaque ea et aperiam a porro praesentium laborum culpa in qui perferendis adipisci labore ut voluptatem nisi quod atque aut voluptatem eveniet autem impedit blanditiis provident voluptatem repudiandae doloremque laudantium cupiditate ut dolore corrupti rerum commodi libero cumque possimus quidem porro aut asperiores quidem unde et hic debitis illo ab autem voluptate autem magni aspernatur natus nulla incidunt fuga et deserunt beatae ab fuga voluptas sint consectetur temporibus voluptas est alias est sequi laboriosam tenetur et aut facere natus adipisci quia amet autem sapiente ipsam dolores suscipit voluptatum sit autem aut reprehenderit porro dicta ea ullam deserunt quod sapiente odio ipsam necessitatibus iusto rerum nam.","address":{"streetAddress":"17109 Isaias Divide Apt. 981","city":"922 Koss Isle Suite 952\nHoweberg, AK 30729","postcode":"72399","state":"Pennsylvania"},"article":{"id":9,"title":"Autem odit quod sed.","text":"Ut voluptate alias et et amet ea necessitatibus unde ut dolore iure enim voluptatem laudantium hic enim quibusdam eius facere adipisci dolorum voluptates dolor a et sit eum praesentium delectus fugit suscipit et explicabo voluptatem quam eum et error et nulla adipisci molestiae voluptatibus iusto sed adipisci et accusamus possimus sit et nisi ad quidem dignissimos quidem provident aliquid debitis neque in suscipit qui ad rem veniam consequatur quia neque laborum inventore quos dolorem perferendis voluptatem voluptas nam cum unde sunt amet deleniti et dolorum sit eveniet quia et minus quae id nulla nulla esse laudantium repellat eos ut eius reprehenderit sint est et asperiores sed adipisci rerum quam temporibus nobis ut similique corporis est itaque blanditiis expedita et omnis hic vel facere dignissimos inventore temporibus dolores fugiat itaque autem nisi magni distinctio vel quo sit voluptatem nisi magni enim qui odio omnis sunt corrupti eum dolorem quos est non est odio eveniet consequuntur ab sint fugiat deserunt sit perspiciatis voluptas nihil consequuntur maxime possimus quisquam qui ut non dignissimos suscipit magni voluptatem aliquid autem in occaecati quae dolor voluptatem illo blanditiis et voluptatem praesentium accusantium adipisci libero occaecati est quis qui velit soluta illum optio tempore enim eveniet dolores doloribus culpa eos quos asperiores et vitae est asperiores perspiciatis temporibus nulla ipsam et quis omnis vitae aut enim occaecati molestias omnis ut excepturi tempore consequatur neque reprehenderit alias in minima repellendus fuga molestias at placeat nulla et quia ipsam ut excepturi praesentium culpa est doloremque possimus autem delectus et perspiciatis ipsa in nemo magni nostrum officiis sapiente porro repellat in voluptate et maxime incidunt consequatur est consequatur facere voluptatem culpa dolorem consequatur molestias harum laboriosam dolores illo ipsam provident voluptatem est iusto nihil esse eum nesciunt et est a aut fuga est voluptas ut sed et quaerat impedit nemo at eos nemo quod laboriosam molestias non asperiores dignissimos aliquid dolores sequi quo veritatis libero beatae rem quidem vel omnis odio magni error quo et sequi omnis quod iure itaque est ut neque qui rerum sed impedit quo voluptas doloribus explicabo minus dolorem maxime distinctio qui accusantium delectus molestias nam explicabo quia est omnis inventore voluptatem ducimus eos porro nulla voluptatibus ut molestiae dicta cum dolorum tempore corporis est ducimus fugit a repellat dolorum veritatis et odio voluptas nisi iusto nam rerum occaecati illo ullam labore incidunt dolorem quasi odit in doloremque voluptas eum laborum eius quia ut quasi sunt culpa fugit repudiandae enim quibusdam quidem iure quae perferendis quis reprehenderit occaecati rerum est perferendis dolore alias animi occaecati sequi occaecati architecto distinctio ut dolor vitae assumenda et aliquam earum occaecati accusamus quam et aperiam voluptatibus eum ut atque dolores nam est expedita maxime est voluptates officiis molestias eaque autem est qui et consequatur perspiciatis totam minus sapiente quod velit minima ut itaque aliquam similique eligendi quas autem labore voluptas natus quam nam nemo consequatur aut consectetur et cum tenetur molestiae vel laudantium tenetur facere voluptatibus enim deserunt hic corrupti incidunt at in voluptatem cum laudantium rem labore eos maxime itaque qui excepturi fugiat ab consequuntur laudantium et autem veritatis in consectetur tenetur rem soluta quidem eligendi facere dolor earum ipsa hic laboriosam quaerat at rem ipsam explicabo corporis eius nostrum sunt necessitatibus tempore saepe a inventore qui iure reprehenderit molestiae numquam consequatur est possimus ducimus aliquam quo ex ut quia eos libero recusandae tempore pariatur consequatur omnis consequatur animi ullam voluptatem qui consequatur nihil quisquam enim sapiente quisquam ducimus animi accusamus voluptatibus quaerat animi accusantium dicta laborum vel beatae qui amet ut explicabo saepe sapiente fugit voluptate repudiandae est illum officiis veritatis nihil sunt quaerat corrupti quaerat occaecati voluptatum id dignissimos doloribus ea incidunt iusto est quibusdam quia vero reiciendis quia voluptas sunt ea praesentium qui illum et necessitatibus voluptatem dolorem sit iusto reiciendis ipsam occaecati distinctio iusto non adipisci fugit alias quia eius sint mollitia dolor molestiae facilis voluptatem sed aut necessitatibus ut fugiat qui magnam quis et sint."}}