{"firstName":"Casper","lastName":"Fadel","email":"rhudson@harris.biz","phone":"563.350.8457 x0382","bio":"Repellat porro fugit fuga sunt odit dolor amet modi. Possimus quis molestias deserunt adipisci. Voluptate ut fugiat sunt.","price":53040619,"is_verified":false,"company":"Medhurst-Bruen","time":1525002621,"about":"Aspernatur aut maxime beatae natus aut temporibus sed qui delectus iste aspernatur minus ut odio earum blanditiis est reprehenderit quas qui velit dolores ea eos consectetur porro quo consequuntur velit voluptatem ut vero sit et laboriosam hic qui ipsam autem laboriosam quia fugiat est doloremque in nobis rerum dolores voluptas nobis est ut exercitationem itaque error ut officiis voluptatem maxime et voluptatem ea est distinctio qui deserunt excepturi accusamus consectetur labore laborum amet necessitatibus numquam iste doloribus hic molestiae aut sit placeat quasi animi ex cum distinctio suscipit tempora accusamus rerum asperiores et nihil est quis ipsa eveniet assumenda in corporis aut id alias aliquid saepe autem quas adipisci libero et fugiat labore eligendi aut repudiandae quas repudiandae placeat aut nisi veritatis ex fuga quos esse adipisci atque voluptatem aut eveniet corporis at et nulla est natus amet odit sed nihil et quaerat ut quia corporis repudiandae fugiat quasi iusto quae reiciendis porro deleniti laboriosam consequatur id quibusdam ut enim aperiam dolor mollitia illo est tenetur ad culpa est natus id sint ut reiciendis dolor debitis doloremque vitae laborum assumenda fugiat ut consequatur ducimus quia consequuntur ut sit aut velit qui sed veniam beatae quas voluptates ipsam quaerat enim a dolore a est fugit est aut iure culpa placeat qui voluptatem mollitia quia exercitationem et dicta odio magnam deleniti sit est qui sit labore ea dolorum debitis aut est sed necessitatibus et ut ipsum quia facere dolor nam dolorem sit architecto blanditiis iure sit qui expedita recusandae ab et vitae et qui excepturi omnis consequuntur nemo corporis exercitationem aut et praesentium et incidunt quis consequuntur laboriosam ea qui ad quas corporis delectus tenetur assumenda et modi temporibus odit voluptas ut ipsa dolorum consequatur qui voluptatum laborum ea ut et at dolores et temporibus eaque dolorem et perspiciatis repellendus ut dolor qui libero ea libero aut non corporis voluptates reiciendis sed fugiat ea debitis omnis ullam iure sit voluptas iure omnis iure aut esse ea omnis voluptatem in animi est quis eligendi qui aut fugiat quisquam et labore quis voluptas unde enim provident iste quibusdam eveniet molestiae consequatur sunt provident distinctio asperiores minima ipsam aliquid expedita quis aliquid nam aperiam quas consectetur in et officia sed veritatis quasi aut qui officiis quis ipsum porro id inventore qui ut voluptas quod omnis eos rerum iure quae vel neque explicabo odit cupiditate repudiandae amet incidunt et blanditiis quo non id eveniet laudantium est aut et et ad quo quas corrupti ab earum pariatur ut nostrum fugiat labore laboriosam iusto molestiae repellendus ut iure suscipit accusamus non velit iure fuga explicabo ratione id sit recusandae unde provident laudantium sint et vero aut maiores quam quam inventore qui est iure aut veniam enim voluptatem dolores suscipit tempore voluptas veniam asperiores sint nesciunt soluta aspernatur qui officia sapiente ipsa incidunt laboriosam vel nostrum blanditiis porro odit quidem cum iste et libero aut sed voluptatem numquam non quis quo velit est itaque incidunt ut molestiae non rerum qui asperiores et numquam in possimus dicta culpa voluptatem autem explicabo nemo eos aperiam assumenda quia qui aspernatur ex nisi libero magnam reprehenderit saepe quo in sed ut nam dolorem vel numquam consequatur sunt quo quisquam et facilis est incidunt minus quia quia omnis aut rerum odio nihil quod reprehenderit autem illum laudantium aut quo optio voluptatem distinctio quidem doloremque iusto delectus provident possimus unde quod natus voluptas et architecto ut modi nostrum in eos quidem nulla expedita eligendi voluptatem itaque aut praesentium provident omnis magnam nihil vel ducimus occaecati eveniet error vero asperiores vitae incidunt porro dolore occaecati accusantium ex voluptatum nemo est ipsum sed necessitatibus nostrum veritatis nisi et.","address":{"streetAddress":"4247 Zachariah Ports","city":"72735 Hackett Harbor\nNorth Eldridge, DE 98042-5477","postcode":"85493","state":"Massachusetts"},"article":{"id":9,"title":"Voluptatibus et et in dolore.","text":"Voluptas voluptate ipsa ut cumque sequi ipsam fuga necessitatibus est molestias voluptatibus nostrum qui quasi voluptas et ducimus perspiciatis cum libero ab quis et sequi consequatur enim sit ut quis voluptatem sequi et odio blanditiis enim harum non eos quas est doloribus omnis rerum cupiditate qui velit ratione aut ipsa repudiandae non sit sint error et provident sed sapiente minus aut voluptates laboriosam officia tempora pariatur iure qui adipisci nemo quos nobis ea voluptates dolore molestiae error ut aut quis repellat nemo in ratione reprehenderit ut et ad omnis minus illo non dolorem odio dolore sed ad saepe consequatur suscipit unde quis enim corporis vel sed laborum sed quaerat sint aut animi quam doloribus animi quo qui sit id molestiae quaerat et a qui dolores sed corporis quis eius possimus et in eos dicta cum quo sapiente blanditiis quidem quis velit et modi mollitia atque culpa alias occaecati quae qui et ab dignissimos modi quo molestiae non a totam esse est in reiciendis sunt eos quis qui ea provident beatae cumque quo magnam et itaque harum excepturi numquam nemo tenetur est reprehenderit iusto placeat animi ea consequatur et dolor assumenda consequuntur modi sunt consequuntur nihil maxime et non quos ipsa quasi cupiditate ratione a laborum eum corporis asperiores dolore ipsum dolorem dolores asperiores aperiam minus voluptatibus quidem voluptatem at ipsum hic reiciendis iure rerum facere ab voluptates dolor omnis quos dolorem animi impedit et quia sint esse consequatur hic voluptatibus aliquid omnis neque eligendi molestiae doloremque quaerat adipisci omnis culpa perspiciatis id sit debitis qui rem incidunt aut repudiandae voluptate dolore dicta aut molestiae quia perspiciatis culpa consequatur non ad iure nesciunt accusamus autem sed nobis dolorem voluptatem amet aut at neque minus sit sapiente accusantium labore non quia mollitia et porro ea illo aliquam perspiciatis eos eos expedita et hic enim mollitia porro est optio voluptatem cum quaerat iste doloribus molestias et distinctio error eos ratione repudiandae et quia pariatur unde nihil alias beatae illum quam velit in dolor dolorum quas nihil dolorem id enim est aperiam fugiat modi itaque voluptas tenetur temporibus nam voluptatem laborum natus omnis asperiores rem ut dolores ipsum voluptatem qui iusto fugiat nemo et voluptatum quia qui enim et dolorum optio fugiat laboriosam qui culpa natus cum sit veritatis in asperiores voluptas aliquam saepe aliquid et voluptates libero dolor aut aliquid excepturi ipsam aut facere perspiciatis vel maiores vel repudiandae quo porro quo autem et quod illo alias quaerat nobis dignissimos hic est est quos aut reiciendis aut ab velit voluptatem amet qui harum dolore maxime sapiente nulla harum dolorem veniam iste omnis perspiciatis sit id placeat ea corporis qui fugit labore est quasi nihil voluptatem quidem aut laudantium omnis provident et ut doloribus repudiandae enim consequatur error vel et tenetur ex repudiandae aperiam odit eveniet expedita provident eum enim ea omnis beatae nostrum eligendi omnis assumenda eos quia expedita quibusdam tempora non eos ut quos possimus quia iusto dignissimos perspiciatis sint voluptas eius deleniti quibusdam tempora in sed qui itaque non commodi vel voluptatem sit eius at autem beatae esse laudantium rerum excepturi culpa animi cum amet odit quasi enim facere et consequuntur qui sed magnam nobis officiis ducimus nam aut quos blanditiis officia eos ut consequatur natus rerum rerum voluptates dolorem ex autem quasi laudantium veritatis dolor at ea ut vel dolor et sed repellat corporis rem quo a et voluptatibus perferendis ea sed et deleniti hic nulla libero omnis odit vel vitae voluptatibus et aspernatur quo sit facere nemo exercitationem aut itaque enim consequatur officia non odio qui omnis adipisci quia odit voluptatibus quam non laudantium sint mollitia animi velit debitis deserunt sed dicta qui voluptas quia repellendus ipsum voluptatem quos aspernatur magni vel nesciunt harum consequatur inventore unde ut sequi ut beatae totam aliquid corporis earum vel qui dolorum quasi et consequatur omnis corrupti illo qui omnis nam non amet qui ducimus rem alias dolorum culpa iure laboriosam laborum saepe minima blanditiis laboriosam dolor harum ut incidunt doloribus commodi ipsum quia iure quo quam neque unde minus hic qui omnis neque odio dolorem itaque iure sit totam ducimus voluptates explicabo vel et autem sint quas et magnam vel vitae aliquid quaerat est blanditiis rem voluptatem ipsum numquam animi consequatur sit occaecati enim ipsum aut ea omnis qui molestiae repellat corrupti sapiente minus tempora consectetur vitae impedit sit molestiae ipsam harum doloribus et rerum consequatur voluptatem ut dicta quidem voluptas facere et soluta eligendi debitis magnam dolores dolor eum eius tempora tempore tempore vitae libero doloremque et sed enim incidunt atque magnam pariatur voluptas animi in at at amet aut voluptatum dolorem nisi eaque eveniet beatae assumenda porro porro et qui itaque aut doloremque ut odio ut commodi voluptatem suscipit quam perferendis id eveniet modi provident neque ut non autem exercitationem qui fuga ipsam enim non cumque omnis sequi occaecati quo qui dolor qui aperiam ullam aut quia beatae ut veniam ipsa molestiae ut molestias commodi distinctio incidunt autem enim ex nesciunt vel ullam nihil minus sunt consequatur iusto saepe temporibus dolor modi accusamus vel velit odit in est distinctio atque at voluptatem soluta totam consequatur voluptate excepturi expedita asperiores et alias molestias quo ut natus sint est quis itaque dolores sed quasi laudantium quod ea perferendis sit praesentium quae quos rerum esse reiciendis error mollitia accusamus consequatur nostrum ab quod harum vitae explicabo aliquam aut perspiciatis sunt ad accusantium praesentium ut vitae omnis ut eum vitae culpa molestiae dolorum aut aut quisquam consequuntur sed aliquam dicta tempora quia quisquam dolorem dolor sint beatae qui eos impedit ut tenetur tempora ducimus culpa corrupti consequatur dicta sit reiciendis qui repudiandae impedit enim officiis et ex nobis est aut consequatur sit possimus sapiente cumque qui et recusandae velit officia dicta eum quia dolores dolores deserunt commodi dolorum ab doloremque et non omnis vero exercitationem fuga nemo ab architecto sit vel deserunt amet esse ut reiciendis nisi veniam porro perspiciatis omnis error esse rerum ut unde possimus mollitia unde illum quibusdam ea non est velit fugiat voluptatibus enim voluptatem laborum modi quibusdam sit voluptas commodi voluptatem doloribus quasi explicabo voluptatem molestiae est et eligendi qui ipsum quas quibusdam possimus adipisci error temporibus voluptatem dolor odit saepe et eius ea adipisci sit excepturi ad officiis debitis quis repellendus consequatur asperiores harum impedit ipsa reiciendis praesentium tenetur rerum impedit harum odio qui et et iusto iure voluptatibus minus consectetur quia ut atque repellat est ex et dolor qui quisquam laborum qui at facilis mollitia similique explicabo cum dolores eos ipsum voluptatem dolorum et praesentium dignissimos alias deleniti dignissimos ratione qui incidunt facilis dignissimos ut voluptatum voluptas porro id ipsam deserunt aut est tempore sed nihil laboriosam rem quas et illum non qui asperiores cupiditate tenetur aperiam accusantium quidem vel earum et molestias ea tempora enim itaque et exercitationem quibusdam eaque nostrum molestiae suscipit nihil velit fuga non nihil dolores quibusdam quos quasi facere atque dignissimos enim nobis dolor ab architecto temporibus impedit voluptates at quo nulla ea est unde labore consequuntur in similique ut sint minima dolorum vel ab consequuntur ducimus aut et aut ad reiciendis excepturi voluptates rerum neque impedit labore adipisci nam et voluptatem velit doloremque excepturi aut soluta doloribus sed id assumenda aperiam aut ex ut nam nihil ratione error rerum quas ut cupiditate rerum debitis mollitia modi rem ut vel nulla voluptates ducimus repellendus iusto enim earum dolor blanditiis aut soluta tenetur eaque non quis et modi eius animi quae repellendus vitae ipsa vero sit hic et sit enim ipsa id ipsum est suscipit sapiente ut nesciunt assumenda sit non nihil praesentium non est et est distinctio et itaque dolor nulla a est ratione sint et molestiae ut ipsa dolores et est sunt exercitationem commodi debitis quas voluptas placeat nihil non enim adipisci nobis numquam dolores repellendus amet totam vero qui adipisci asperiores veritatis rem molestias sed id et minima consequuntur minima impedit voluptatem facere excepturi voluptates vel aspernatur hic aspernatur molestiae non rerum iure laboriosam eos quibusdam necessitatibus velit ab sit quisquam itaque non quo ut quis minus nam voluptate totam repudiandae exercitationem eius sunt qui aliquam et molestiae temporibus excepturi mollitia."}}