{"firstName":"Dameon","lastName":"Smitham","email":"oconner.misty@yahoo.com","phone":"+1-428-988-5410","bio":"Sunt veritatis vel autem. Enim molestiae ex voluptatum et. Placeat optio nihil unde soluta neque velit possimus. Officia libero quos et.","price":8062247,"is_verified":true,"company":"Gulgowski Group","time":1525002753,"about":"Harum eos perferendis qui consequuntur aut dolor veritatis rem esse quas dignissimos nemo aliquam sed eos et blanditiis ipsam fuga corrupti voluptatibus amet omnis sit nisi est voluptatum neque consequatur quis fuga ut rem aut placeat quas autem est amet sit molestiae nihil ut illo aut ea cumque sint quia error occaecati adipisci aut dolor itaque voluptatem quia autem sit repudiandae placeat omnis assumenda tempore voluptatem enim ullam praesentium delectus repudiandae earum reiciendis animi enim fuga sed non aspernatur accusamus dignissimos ut quae praesentium ea odit eaque voluptatem a ipsam odio aut quisquam sapiente adipisci aperiam dolores nisi aut nemo qui rerum aliquam quasi dicta debitis amet ea et tempora facilis corporis vel ut sunt sint et expedita ipsum voluptatum voluptates fugiat iure voluptatem ipsam dignissimos dignissimos et recusandae voluptatem neque aperiam officiis tempore inventore saepe architecto laborum accusantium impedit optio optio eos quas sunt tenetur veritatis reiciendis ut voluptatem suscipit eos eos reiciendis voluptatem velit aliquam odit quibusdam corporis voluptatem et enim qui qui tempore facilis ut repudiandae blanditiis aut ab quo eius ut et est consequuntur quas dignissimos voluptate ea eius magnam odio laborum id in exercitationem cum atque dolorem tempora voluptas quae officia minima quo illum quia sed magnam omnis sint aliquid dignissimos provident error sapiente at et iusto iste magni alias qui architecto dignissimos fuga ipsum dicta eos est nam quidem repudiandae sunt iusto dolores est at voluptatibus numquam natus rerum quis qui aliquid non molestiae sit est qui et repellendus vitae velit excepturi expedita cumque aspernatur in architecto et ut nihil modi enim consequatur molestiae quia expedita ut sit voluptatum quo non quam placeat qui aut in aut laudantium sit vel distinctio neque consequatur autem alias dolore ipsa maxime dolorem autem nam quis vel quia dolorum velit exercitationem iure mollitia cum dolor sit nobis sit assumenda quidem pariatur in suscipit illo aut vero repellendus sapiente hic qui qui sed voluptatem vel molestias quibusdam earum quae aut sed sapiente facilis vel et quia voluptatem aut voluptatibus voluptatem sint eaque ut eveniet sint saepe quisquam odio sapiente enim quo quidem numquam ratione soluta dignissimos laborum voluptatum laboriosam sit animi quae laborum ipsam asperiores ut placeat consectetur nemo nemo eaque consectetur explicabo voluptatem non earum et voluptates alias architecto occaecati pariatur assumenda cupiditate quia quidem est doloribus tenetur non deserunt architecto tenetur nisi sapiente illo voluptatibus blanditiis in officiis nihil et veritatis odio voluptas sed ratione iure dolorum error saepe aliquid id eaque est aut libero eum non nemo quo totam delectus consequatur quo voluptas et cupiditate id ducimus dolorem fugit aliquam cum modi minima quas corporis hic quia accusantium tempora occaecati magnam placeat ad consequuntur sunt fugit voluptatibus voluptatem modi ab sapiente molestiae esse rerum est deleniti quia fugiat eius recusandae quia eligendi repellendus consequuntur perferendis iure voluptatum.","address":{"streetAddress":"945 Twila Shores Apt. 275","city":"546 Ambrose Ports Suite 818\nPort Diana, DE 57535","postcode":"01866-7287","state":"South Dakota"},"article":{"id":9,"title":"Est dolores accusamus voluptatum corporis.","text":"Dolor et quaerat fugiat maxime eos voluptatibus repudiandae consequatur nihil fugit ut adipisci voluptas omnis alias impedit commodi ipsa blanditiis quae eveniet tenetur laboriosam voluptatem et molestiae nam asperiores ea nulla fugiat nam consequuntur explicabo ex autem perferendis aut quam ut voluptatem sed soluta soluta enim non et voluptas quas ut occaecati accusamus sint vero voluptas laudantium quod quibusdam iste iure ut in rerum sit dolorem iusto aut omnis sit sit nisi in vel laborum id minus fuga ducimus libero autem adipisci consequatur atque magni qui qui eos doloribus distinctio et harum quasi illo officia sunt et ex debitis alias maxime ratione itaque facere dolor nihil voluptatem accusantium quo qui illum veniam ullam architecto repudiandae corporis pariatur id sequi fuga quia necessitatibus voluptas aliquid qui amet accusamus et sapiente sunt occaecati sequi molestiae omnis voluptas quam laudantium excepturi vitae laborum facilis tempore dignissimos sed nam accusamus est officiis cumque occaecati molestias non est quis quibusdam quae sed eaque dolorem reprehenderit nesciunt dolorem delectus eum at temporibus praesentium architecto enim repellendus exercitationem exercitationem magni molestiae totam natus doloremque dolor corrupti dolorum amet earum velit quasi soluta id quia accusantium neque placeat similique at iure id nemo ut dolores voluptatem laudantium voluptatem quo ut qui excepturi eveniet modi possimus et repellat in minima ut mollitia aliquam quidem et odit ipsum voluptatem ut in autem esse minus ea possimus rerum facilis enim voluptatem quis consectetur hic quo natus est similique aut et autem perferendis dolorem labore qui non ut non repudiandae suscipit ex nemo officiis dolor facere similique voluptas amet officiis nisi et autem est ea nobis magni aliquam nam odit ipsum et adipisci temporibus ut qui et sequi totam molestias rerum est ut et voluptas ut et laborum odit debitis harum et velit officiis delectus vitae corrupti voluptatem consectetur deleniti molestiae in illo earum tempore enim qui veritatis ab neque nihil sed rerum sunt eos eum quia blanditiis sunt repudiandae molestiae cumque quia neque deserunt aut eum aliquam ut enim aut et voluptatem corporis eos est quo et expedita qui perferendis consectetur est doloribus odit qui ut qui sunt repellat ut ipsam ut nisi adipisci voluptatem quod qui voluptas exercitationem non quisquam consectetur in nihil magnam quia id non impedit nam eos vel pariatur saepe et aliquid excepturi omnis veritatis atque quis explicabo exercitationem corrupti officia ad saepe dolor aliquam est vel non rem occaecati odit et iste consequuntur sint labore sed velit quae aut veniam dolores quos error dolorum veniam quam labore veritatis magni omnis blanditiis perferendis voluptatem cumque eaque nobis temporibus veniam aut dicta ab eligendi similique doloremque sit numquam et rerum est unde vitae totam quas ut modi quia maxime omnis perspiciatis voluptas aut ad similique tenetur facere eum eum saepe vel id qui provident aut maxime sed adipisci voluptatem eligendi qui consequuntur voluptatibus cum distinctio aut non facere repellendus et voluptas eos sint cum saepe itaque magni amet nesciunt deserunt earum maxime dolor alias maiores qui saepe architecto magnam debitis cumque sint dolores commodi suscipit laborum sed optio sit at sint debitis illum recusandae sed pariatur laudantium exercitationem molestiae atque nihil corporis officiis laboriosam expedita eligendi ut sunt nihil ratione corporis id nemo consequuntur reprehenderit ut eos occaecati ullam architecto officia qui ea rerum inventore magnam qui eius blanditiis officiis est itaque ipsum repellendus aliquid et libero odit aut et ut eius quia excepturi impedit consequatur ut officia dicta porro autem magni molestiae beatae qui libero nisi optio qui qui accusantium est architecto qui enim eaque commodi mollitia culpa incidunt nihil alias corrupti et dolorem sint cum ullam molestiae est in aut explicabo at aut sint ut dicta deserunt ipsam nam amet occaecati hic vero dolor voluptatibus aut dolores fuga adipisci neque est et error voluptatibus eaque vitae non quia omnis aut odio laborum culpa quia quae ipsam fugiat ex ut omnis ipsa non dolor qui aut tempora nemo natus voluptatem vel atque laborum pariatur fugit et quis odio voluptatibus qui qui voluptatem deleniti blanditiis totam quo reiciendis molestiae quia laboriosam soluta numquam quisquam ipsa molestiae nulla minus molestiae aut expedita nulla illum magni voluptatem et voluptatem enim similique provident et aut qui dolorem veniam amet quia molestiae in consequuntur corrupti omnis consequatur et ducimus aliquam magnam debitis est est voluptatem inventore debitis quod cupiditate corporis in cum ducimus perferendis quisquam ut quis odio quaerat aperiam consectetur numquam cumque sit nam voluptatum consectetur quisquam mollitia dolores magni et sint facere laudantium minima ducimus explicabo nihil exercitationem aut inventore ut commodi dolorem voluptatibus minima vel et aut dolore voluptas aperiam molestias illo voluptatem modi repudiandae dolorem possimus optio sunt placeat quaerat ratione voluptas hic molestias quam consequatur et ea veniam ducimus quia eius dolorem quia molestiae dignissimos explicabo impedit ex ab sint laudantium nobis aspernatur nihil aut suscipit qui adipisci laborum non minima in consectetur qui qui voluptates aperiam cum ab et voluptatem qui mollitia voluptatibus enim tempore omnis labore earum explicabo quisquam ipsa optio odit quis omnis accusantium alias alias itaque et quas blanditiis modi reiciendis natus veritatis est sunt consequuntur sed dolores eum animi molestiae et in quasi culpa voluptatem officia minus illum praesentium aliquid aspernatur esse molestias ipsa ratione officia reprehenderit iste natus incidunt doloribus eum sequi quasi doloribus dolorum nostrum consequuntur voluptatibus ut vel quod et culpa animi fugiat quidem tempore voluptatibus repellendus maiores unde dolorem quia quas consequatur quos aperiam expedita id voluptatem cupiditate maiores iure odit voluptate sapiente aut corrupti nam sit tempora ut animi rerum illo ut a corporis unde perferendis pariatur aspernatur doloremque hic facilis reprehenderit libero in facere ut rerum reprehenderit dolorem quasi laudantium consequatur eos et ad beatae sit impedit fugiat illo omnis doloribus est sunt dicta dolores magnam nisi quo qui optio nihil in illo aut maiores omnis in quis est quod aut consectetur harum nostrum autem occaecati eos vitae reprehenderit cum consequatur sed sunt officia modi numquam molestiae quasi minima quidem dolores corrupti quod fugiat dolore eum consequuntur quo ut nihil eum repellat molestias iusto similique cupiditate quisquam laborum delectus cumque tempora nobis et architecto aperiam ut numquam blanditiis debitis enim ipsa vero eum tempora labore eveniet est corrupti non voluptatem vel vero non ipsam et tempore et autem non ipsam sit alias dolores laudantium perferendis nisi dicta nostrum voluptatem dolore molestiae quia quasi voluptas omnis quo deleniti iure omnis sed ipsum qui ratione ad impedit aperiam itaque dolor perspiciatis minima est eaque alias sequi maxime nam quae dicta repellendus possimus natus delectus necessitatibus quam quasi iste nesciunt quae explicabo cumque sunt veritatis omnis nisi reiciendis ut et incidunt perferendis dolores harum eum natus ad quia et et temporibus aut et non minima molestiae voluptatem non perspiciatis fuga dolor asperiores error ut omnis et qui quasi iste aut voluptas quia corrupti quae sunt quis unde aut nulla incidunt et sunt totam recusandae amet tempore enim qui vitae est hic porro occaecati repellat sapiente sapiente odit odio laboriosam quia rem fugit sit commodi ut voluptates eveniet temporibus cumque ipsum at vitae ipsam delectus et reprehenderit iure eum pariatur qui ipsum earum praesentium officia sed excepturi adipisci et error error vitae similique perferendis officiis blanditiis quia accusamus est voluptas eos nostrum ut possimus amet rerum accusamus qui quibusdam aliquid eum fugiat non beatae in atque et animi commodi tempora aliquam odit enim cumque sapiente ad ut debitis dolore nam quo."}}